FileOpen.py
FileOpener-0.3.dist-info/LICENSE.txt
FileOpener-0.3.dist-info/METADATA
FileOpener-0.3.dist-info/WHEEL
FileOpener-0.3.dist-info/top_level.txt
FileOpener-0.3.dist-info/RECORD
