Metadata-Version: 2.1
Name: FileOpener
Version: 0.3
Summary: Converts excel to Data Frame
Home-page: UNKNOWN
Author: UNKNOWN
Author-email: UNKNOWN
License: UNKNOWN
Platform: UNKNOWN
Requires-Dist: xlrd (==1.2.0)
